project3/src/design.v
module  shft_mod(
input clk,
input rstn,
input load, dir,
input [7:0] LD,
output cout
);

reg [7:0] shft_reg;

always @(posedge clk or negedge rstn)
begin
 if(~rstn)
  begin
   shft_reg <= 8'h00;
  end
 else
  begin
   if(load)
    shft_reg <= LD[7:0];
   else
    if(dir)
     shft_reg[7:0] <= {1'b0, shft_reg[7:1]};
    else
     shft_reg[7:0] <= {shft_reg[6:0], 1'b0};
  end
end

assign cout = dir ? shft_reg[0] : shft_reg[7];

endmodule

project3/tb/design_tb.v
module shft_tb();
reg clk, rstn;
reg load, dir;
reg [7:0] LD;
wire cout;

shft_mod dut0(.clk(clk), .rstn(rstn), .load(load), .dir(dir), .LD(LD), .cout(cout));

initial
begin
 clk = 0;
 forever #5 clk = ~clk;
end

initial
begin
 $dumpfile("shft.vcd");
 $dumpvars(0,shft_tb);

 rstn = 0; load = 0; dir = 1; rstn = 1;

 dir = 1'b1; // RIGHT shift 
 #500; LD = 8'hA9;
 #500; 
 @(posedge clk); #1;
 load = 1'b1;
 @(posedge clk); #1;
 load = 1'b0;
 
 #500; 
 dir = 1'b0;  // LEFT shift
 #500; LD = 8'h56;
 #500; 

 @(posedge clk); #1;
 load = 1'b1;
 @(posedge clk); #1;
 load = 1'b0;

 #5000;
 $display("\n**************************\n");
 $display("finishing RUN ... Good Bye \n");
 $display("\n**************************\n");
 $finish;
end

endmodule

project3/shft.vcd
$date
	Sun Mar  1 15:35:40 2020
$end
$version
	Icarus Verilog
$end
$timescale
	1s
$end
$scope module shft_tb $end
$var wire 1 ! cout $end
$var reg 8 " LD [7:0] $end
$var reg 1 # clk $end
$var reg 1 $ dir $end
$var reg 1 % load $end
$var reg 1 & rstn $end
$scope module dut0 $end
$var wire 8 ' LD [7:0] $end
$var wire 1 # clk $end
$var wire 1 $ dir $end
$var wire 1 % load $end
$var wire 1 & rstn $end
$var wire 1 ! cout $end
$var reg 8 ( shft_reg [7:0] $end
$upscope $end
$upscope $end
$enddefinitions $end
#0
$dumpvars
b0xxxxxxx (
bx '
1&
0%
1$
0#
bx "
x!
$end
#5
b0xxxxxx (
1#
#10
0#
#15
b0xxxxx (
1#
#20
0#
#25
b0xxxx (
1#
#30
0#
#35
b0xxx (
1#
#40
0#
#45
b0xx (
1#
#50
0#
#55
b0x (
1#
#60
0#
#65
0!
b0 (
1#
